smooth_migrations/__init__.py
smooth_migrations/context.py
smooth_migrations/exceptions.py
smooth_migrations/fields.py
smooth_migrations/management/__init__.py
smooth_migrations/management/commands/__init__.py
smooth_migrations/management/commands/apply_migrations.py
smooth_migrations/management/commands/show_migration_changes.py
smooth_migrations/models.py
smooth_migrations/utils.py
django_smooth_migrations-0.2.0.dist-info/LICENSE
django_smooth_migrations-0.2.0.dist-info/METADATA
django_smooth_migrations-0.2.0.dist-info/WHEEL
django_smooth_migrations-0.2.0.dist-info/RECORD
