Metadata-Version: 2.3
Name: django-smooth-migrations
Version: 0.2.0
Summary: Django library for backward-compatible model changes and automatic migration rollback.
License: MIT
Author: Sergio Torrado
Author-email: sergio.itp16@gmail.com
Requires-Python: >=3.10,<=3.13
Classifier: License :: OSI Approved :: MIT License
Classifier: Programming Language :: Python :: 3
Classifier: Programming Language :: Python :: 3.10
Classifier: Programming Language :: Python :: 3.11
Classifier: Programming Language :: Python :: 3.12
Classifier: Programming Language :: Python :: 3.13
Requires-Dist: django (>=4.0,<6.0)
Project-URL: Homepage, https://github.com/serivt/django-smooth-migrations
Project-URL: Repository, https://github.com/serivt/django-smooth-migrations
